env_should_be/__init__.py
env_should_be/cli.py
env_should_be/description.py
env_should_be/exception.py
env_should_be/utils.py
env_should_be-0.2.7.dist-info/LICENSE
env_should_be-0.2.7.dist-info/METADATA
env_should_be-0.2.7.dist-info/WHEEL
env_should_be-0.2.7.dist-info/entry_points.txt
env_should_be-0.2.7.dist-info/top_level.txt
env_should_be-0.2.7.dist-info/RECORD
