Metadata-Version: 2.1
Name: env-should-be
Version: 0.2.7
Summary: Ship Secure and Streamlined Multi-Environment Specification.
Home-page: https://github.com/wassef911/env_should_be
Author: Wassef911
Author-email: wassef911@gmail.com
Keywords: python3,pypi,package
Classifier: Development Status :: 5 - Production/Stable
Classifier: Intended Audience :: Developers
Classifier: Topic :: Software Development :: Build Tools
Classifier: Programming Language :: Python :: 3 :: Only
Classifier: License :: OSI Approved :: MIT License
Classifier: Operating System :: OS Independent
Requires-Python: >=3.11.4
License-File: LICENSE
Requires-Dist: pyaml
Provides-Extra: dev
Requires-Dist: check-manifest ; extra == 'dev'
Provides-Extra: test
Requires-Dist: coverage ; extra == 'test'
